cpauger/TODO
cpauger/__init__.py
cpauger/augment_image.py
cpauger/crop_obj.py
cpauger/generate_coco_ann.py
cpauger/paste_obj.py
cpauger/visualize.py
cpauger-1.1.2.dist-info/LICENSE
cpauger-1.1.2.dist-info/METADATA
cpauger-1.1.2.dist-info/WHEEL
cpauger-1.1.2.dist-info/RECORD
