Metadata-Version: 2.3
Name: cpauger
Version: 1.1.2
Summary: Handles copy-paste augmentation
License: MIT
Author: linus agbleze
Requires-Python: >=3.9,<4.0
Classifier: License :: OSI Approved :: MIT License
Classifier: Programming Language :: Python :: 3
Classifier: Programming Language :: Python :: 3.9
Classifier: Programming Language :: Python :: 3.10
Classifier: Programming Language :: Python :: 3.11
Classifier: Programming Language :: Python :: 3.12
Classifier: Programming Language :: Python :: 3.13
Requires-Dist: opencv-python (>=4.10.0.84,<5.0.0.0)
Requires-Dist: pycocotools (>=2.0.8,<3.0.0)
Requires-Dist: randimage (>=1.2,<2.0)
Requires-Dist: tqdm (>=4.66.5,<5.0.0)
